{
  "main": {
    "id": "5324373015726ba8",
    "type": "split",
    "children": [
      {
        "id": "4509724f8bf84da7",
        "type": "tabs",
        "children": [
          {
            "id": "e7a7b303c61786dc",
            "type": "leaf",
            "state": {
              "type": "markdown",
              "state": {
                "file": "3 - Estrutura de Dados/Arrays.md",
                "mode": "source",
                "source": false
              },
              "icon": "lucide-file",
              "title": "Arrays"
            }
          }
        ]
      }
    ],
    "direction": "vertical"
  },
  "left": {
    "id": "be0d1ed45b2ff01f",
    "type": "split",
    "children": [
      {
        "id": "08285311d8a8b525",
        "type": "tabs",
        "children": [
          {
            "id": "fca936a7bff14a3f",
            "type": "leaf",
            "state": {
              "type": "file-explorer",
              "state": {
                "sortOrder": "alphabetical",
                "autoReveal": false
              },
              "icon": "lucide-folder-closed",
              "title": "Files"
            }
          },
          {
            "id": "96b0111573279680",
            "type": "leaf",
            "state": {
              "type": "search",
              "state": {
                "query": "",
                "matchingCase": false,
                "explainSearch": false,
                "collapseAll": false,
                "extraContext": false,
                "sortOrder": "alphabetical"
              },
              "icon": "lucide-search",
              "title": "Search"
            }
          },
          {
            "id": "bfbb60960ceaef99",
            "type": "leaf",
            "state": {
              "type": "bookmarks",
              "state": {},
              "icon": "lucide-bookmark",
              "title": "Bookmarks"
            }
          }
        ]
      }
    ],
    "direction": "horizontal",
    "width": 370
  },
  "right": {
    "id": "9aef16c8d2a3d563",
    "type": "split",
    "children": [
      {
        "id": "655f27943543ee38",
        "type": "tabs",
        "dimension": 29.276315789473685,
        "children": [
          {
            "id": "655a1aa9d561026b",
            "type": "leaf",
            "state": {
              "type": "backlink",
              "state": {
                "file": "Random/Brainstorm.canvas",
                "collapseAll": false,
                "extraContext": false,
                "sortOrder": "alphabetical",
                "showSearch": false,
                "searchQuery": "",
                "backlinkCollapsed": false,
                "unlinkedCollapsed": true
              },
              "icon": "links-coming-in",
              "title": "Backlinks for Brainstorm"
            }
          },
          {
            "id": "92619fecd411bdc9",
            "type": "leaf",
            "state": {
              "type": "outgoing-link",
              "state": {
                "file": "Random/Brainstorm.canvas",
                "linksCollapsed": false,
                "unlinkedCollapsed": true
              },
              "icon": "links-going-out",
              "title": "Outgoing links from Brainstorm"
            }
          },
          {
            "id": "e24b8793ebd4db31",
            "type": "leaf",
            "state": {
              "type": "tag",
              "state": {
                "sortOrder": "frequency",
                "useHierarchy": true
              },
              "icon": "lucide-tags",
              "title": "Tags"
            }
          },
          {
            "id": "39fe7aef525cfe0f",
            "type": "leaf",
            "state": {
              "type": "outline",
              "state": {
                "file": "2-Basico_Csharp/Resumo.canvas",
                "followCursor": false,
                "showSearch": false,
                "searchQuery": ""
              },
              "icon": "lucide-list",
              "title": "Outline of Resumo"
            }
          },
          {
            "id": "658ec0b050d7a52a",
            "type": "leaf",
            "state": {
              "type": "git-view",
              "state": {},
              "icon": "git-pull-request",
              "title": "Source Control"
            }
          }
        ],
        "currentTab": 4
      },
      {
        "id": "350efa17d6fe71ef",
        "type": "tabs",
        "dimension": 25.767543859649123,
        "children": [
          {
            "id": "24369715c69873e3",
            "type": "leaf",
            "state": {
              "type": "calendar",
              "state": {},
              "icon": "calendar-with-checkmark",
              "title": "Calendar"
            }
          }
        ]
      },
      {
        "id": "20644356191ac69f",
        "type": "tabs",
        "dimension": 44.95614035087719,
        "children": [
          {
            "id": "e7a7b303c61786dc",
            "type": "leaf",
            "state": {
              "type": "graph",
              "state": {},
              "icon": "lucide-git-fork",
              "title": "Graph view"
            }
          }
        ]
      }
    ],
    "direction": "horizontal",
    "width": 408
  },
  "left-ribbon": {
    "hiddenItems": {
      "switcher:Open quick switcher": false,
      "canvas:Create new canvas": false,
      "daily-notes:Open today's daily note": false,
      "templates:Insert template": false,
      "command-palette:Open command palette": false,
      "table-editor-obsidian:Advanced Tables Toolbar": false,
      "obsidian-git:Open Git source control": false,
      "homepage:Open homepage": false,
      "graph:Open graph view": false,
      "obsidian-kanban:Create new board": false
    }
  },
  "active": "e7a7b303c61786dc",
  "lastOpenFiles": [
    "3 - Estrutura de Dados/DSA - Estrutura de dados.md",
    "3 - Estrutura de Dados/Arrays.md",
    "3 - Estrutura de Dados/images/array-predefined-explanation.png",
    "3 - Estrutura de Dados/images",
    "Dotnet Software Engineer.md",
    "7 - Minimal APIs/Minimal API.md",
    "7 - Minimal APIs/9 - Conectando Model e DTO.md",
    "7 - Minimal APIs/10 - Criando um Service.md",
    "7 - Minimal APIs/images/16-install-automapper.png",
    "7 - Minimal APIs/images/16-automapper-search.png",
    "7 - Minimal APIs/images/16-nugget-package-manager.png",
    "7 - Minimal APIs/8 - Trabalhando com DTOs.md",
    "7 - Minimal APIs/images/15-dto-class2.png",
    "7 - Minimal APIs/images/15-dto-class.png",
    "7 - Minimal APIs/images/15-dto-folder.png",
    "7 - Minimal APIs/7 - Criando Models.md",
    "Random/DTOS EXPLANATION WITH RECORDS.md",
    "Random/Aleatórios.md",
    "2 - Básico de Csharp/6 - Tipos na memória/Tipos de Valor (Stack).md",
    "2 - Básico de Csharp/6 - Tipos na memória/Tipos de Referência (Heap).md",
    "7 - Minimal APIs/6 - Configurando SQLite no projeto.md",
    "7 - Minimal APIs/5 - Instalando EF Core.md",
    "7 - Minimal APIs/4 - Instalando Swagger.md",
    "7 - Minimal APIs/3 - Primeira config do Program.cs.md",
    "7 - Minimal APIs/2 - Entendendo projeto inicial.md",
    "7 - Minimal APIs/1  - Criando pelo Visual Studio 2022.md",
    "2 - Básico de Csharp/Básico de Csharp.md",
    "7 - Minimal APIs/images/14-basic-file.png",
    "7 - Minimal APIs/images/14-new-data-class.png",
    "7 - Minimal APIs/images/14-creating-data-class.png",
    "8 - Banco de dados/SQLite/Instalando SQLite.md",
    "7 - Minimal APIs/5 - Criando Model.md",
    "8 - Banco de dados/SQLite/Home SQLite.md",
    "8 - Banco de dados/images",
    "8 - Banco de dados/New folder",
    "8 - Banco de dados/SQLite",
    "Untitled",
    "8 - Banco de dados",
    "7 - Minimal APIs/images",
    "7 - Minimal APIs/New folder",
    "2 - Básico de Csharp/13 - Strings/Interpolação de Strings.md",
    "7 - Minimal APIs",
    "2 - Básico de Csharp/13 - Strings/Comparação de Strings.md",
    "2 - Básico de Csharp/12 - GUID/GUID.md",
    "2 - Básico de Csharp/Resumo.canvas",
    "2 - Básico de Csharp/13 - Strings",
    "Random/Brainstorm.canvas"
  ]
}